mani_skill/__init__.py
mani_skill/agents/__init__.py
mani_skill/agents/base_agent.py
mani_skill/agents/base_real_agent.py
mani_skill/agents/multi_agent.py
mani_skill/agents/registration.py
mani_skill/agents/utils.py
mani_skill/agents/controllers/__init__.py
mani_skill/agents/controllers/base_controller.py
mani_skill/agents/controllers/passive_controller.py
mani_skill/agents/controllers/pd_base_vel.py
mani_skill/agents/controllers/pd_ee_pose.py
mani_skill/agents/controllers/pd_joint_pos.py
mani_skill/agents/controllers/pd_joint_pos_vel.py
mani_skill/agents/controllers/pd_joint_vel.py
mani_skill/agents/controllers/utils/__init__.py
mani_skill/agents/controllers/utils/kinematics.py
mani_skill/agents/robots/__init__.py
mani_skill/agents/robots/allegro_hand/__init__.py
mani_skill/agents/robots/allegro_hand/allegro.py
mani_skill/agents/robots/allegro_hand/allegro_touch.py
mani_skill/agents/robots/anymal/__init__.py
mani_skill/agents/robots/anymal/anymal_c.py
mani_skill/agents/robots/dclaw/__init__.py
mani_skill/agents/robots/dclaw/dclaw.py
mani_skill/agents/robots/fetch/__init__.py
mani_skill/agents/robots/fetch/fetch.py
mani_skill/agents/robots/floating_ability_hand/__init__.py
mani_skill/agents/robots/floating_ability_hand/floating_ability_hand.py
mani_skill/agents/robots/floating_panda_gripper/__init__.py
mani_skill/agents/robots/floating_panda_gripper/floating_panda_gripper.py
mani_skill/agents/robots/floating_robotiq_2f_85_gripper/__init__.py
mani_skill/agents/robots/floating_robotiq_2f_85_gripper/floating_robotiq_2f_85_gripper.py
mani_skill/agents/robots/googlerobot/__init__.py
mani_skill/agents/robots/googlerobot/googlerobot.py
mani_skill/agents/robots/humanoid/__init__.py
mani_skill/agents/robots/humanoid/humanoid.py
mani_skill/agents/robots/inspire_hand/__init__.py
mani_skill/agents/robots/inspire_hand/fixed_inspire_hand.py
mani_skill/agents/robots/inspire_hand/floating_inspire_hand.py
mani_skill/agents/robots/koch/__init__.py
mani_skill-3.0.0b22.dist-info/licenses/LICENSE
mani_skill-3.0.0b22.dist-info/licenses/LICENSE-3RD-PARTY
mani_skill-3.0.0b22.dist-info/METADATA
mani_skill-3.0.0b22.dist-info/WHEEL
mani_skill-3.0.0b22.dist-info/top_level.txt
mani_skill-3.0.0b22.dist-info/RECORD
