Metadata-Version: 2.4
Name: mani_skill
Version: 3.0.0b22
Summary: ManiSkill3: A Unified Benchmark for Generalizable Manipulation Skills
Home-page: https://github.com/haosulab/ManiSkill
Author: ManiSkill contributors
Requires-Python: >=3.9
License-File: LICENSE
License-File: LICENSE-3RD-PARTY
Requires-Dist: numpy>=1.22
Requires-Dist: scipy
Requires-Dist: dacite
Requires-Dist: gymnasium==0.29.1
Requires-Dist: h5py
Requires-Dist: pyyaml
Requires-Dist: tqdm
Requires-Dist: GitPython
Requires-Dist: tabulate
Requires-Dist: transforms3d
Requires-Dist: trimesh
Requires-Dist: imageio
Requires-Dist: imageio[ffmpeg]
Requires-Dist: mplib==0.1.1; platform_system == "Linux"
Requires-Dist: fast_kinematics==0.2.2; platform_system == "Linux"
Requires-Dist: IPython
Requires-Dist: pytorch_kinematics==0.7.6
Requires-Dist: nvidia-ml-py
Requires-Dist: tyro>=0.8.5
Requires-Dist: huggingface_hub
Requires-Dist: sapien>=3.0.0; platform_system == "Linux"
Requires-Dist: sapien>=3.0.0.b1; platform_system == "Windows"
Provides-Extra: dev
Requires-Dist: pytest; extra == "dev"
Requires-Dist: black; extra == "dev"
Requires-Dist: isort; extra == "dev"
Requires-Dist: pre-commit; extra == "dev"
Requires-Dist: build; extra == "dev"
Requires-Dist: twine; extra == "dev"
Requires-Dist: stable_baselines3; extra == "dev"
Requires-Dist: nvidia-ml-py; extra == "dev"
Requires-Dist: pytest-xdist[psutil]; extra == "dev"
Requires-Dist: pytest-forked; extra == "dev"
Provides-Extra: docs
Requires-Dist: sphinx==6.2.1; extra == "docs"
Requires-Dist: sphinx-autobuild; extra == "docs"
Requires-Dist: pydata_sphinx_theme; extra == "docs"
Requires-Dist: sphinxcontrib.spelling; extra == "docs"
Requires-Dist: sphinx-autodoc-typehints; extra == "docs"
Requires-Dist: sphinx_copybutton; extra == "docs"
Requires-Dist: myst-parser; extra == "docs"
Requires-Dist: sphinx-subfigure; extra == "docs"
Requires-Dist: sphinxcontrib-video; extra == "docs"
Requires-Dist: sphinx-togglebutton; extra == "docs"
Requires-Dist: sphinx_design; extra == "docs"
Requires-Dist: sphinx-autoapi; extra == "docs"
Dynamic: author
Dynamic: description
Dynamic: description-content-type
Dynamic: home-page
Dynamic: license-file
Dynamic: provides-extra
Dynamic: requires-dist
Dynamic: requires-python
Dynamic: summary
